flask_restful_resource/__init__.py
flask_restful_resource/base_resource/__init__.py
flask_restful_resource/base_resource/base.py
flask_restful_resource/base_resource/exceptions.py
flask_restful_resource/base_resource/mongo_resource.py
flask_restful_resource/base_resource/sql_resource.py
flask_restful_resource/comm/__init__.py
flask_restful_resource/comm/config.py
flask_restful_resource/comm/env.py
flask_restful_resource/comm/get_host_ip.py
flask_restful_resource/comm/logger.py
flask_restful_resource/comm/utils.py
flask_restful_resource/comm/zkCli.py
tests/__init__.py
tests/conftest.py
tests/test_base.py
tests/test_envzk.py
tests/test_mongo.py
tests/test_sql.py
flask_restful_resource_new-0.3.5.dist-info/METADATA
flask_restful_resource_new-0.3.5.dist-info/WHEEL
flask_restful_resource_new-0.3.5.dist-info/top_level.txt
flask_restful_resource_new-0.3.5.dist-info/RECORD
