Metadata-Version: 2.4
Name: flask_restful_resource_new
Version: 0.3.5
Requires-Dist: Flask==2.3.3
Requires-Dist: Flask-RESTful==0.3.10
Requires-Dist: schema==0.7.5
Requires-Dist: marshmallow==3.20.1
Requires-Dist: requests==2.31.0
Requires-Dist: kazoo==2.10.0
Dynamic: requires-dist
